gradedb/__init__.py
gradedb/__version__.py
gradedb/gpa.py
gradedb-1.0.2.dist-info/METADATA
gradedb-1.0.2.dist-info/RECORD
gradedb-1.0.2.dist-info/WHEEL
gradedb-1.0.2.dist-info/entry_points.txt
gradedb-1.0.2.dist-info/top_level.txt
mypackage/__init__.py
mypackage/__version__.py
mypackage/core.py
nblogic/__init__.py
nblogic/__version__.py
nblogic/icit_grade.py
nblogic/klogic_gpa.py
