Metadata-Version: 2.1
Name: gradedb
Version: 1.0.2
Summary: The program that load the CSV file and use them as database. Main function is to Insert / Update / Save course and it's detail and Calculate the GPA from given CSV
Home-page: https://github.com/thanawatpetchuen/gradedb
Author: Thanawat Petchuen
Author-email: thanawat1petchuen@gmail.com
License: MIT
Platform: UNKNOWN
Classifier: License :: OSI Approved :: MIT License
Classifier: Programming Language :: Python
Classifier: Programming Language :: Python :: 3
Classifier: Programming Language :: Python :: 3.6
Classifier: Programming Language :: Python :: Implementation :: CPython
Classifier: Programming Language :: Python :: Implementation :: PyPy
Requires-Python: >=3.6.0
Requires-Dist: art
Requires-Dist: PyInquirer
Requires-Dist: tabulate
Requires-Dist: pandas
Requires-Dist: nblogic
